cerebellum/__init__.py
cerebellum/browser.py
cerebellum/planners/__init__.py
cerebellum/planners/anthropic.py
cerebellum/py.typed
cerebellum/utils.py
cerebellum-0.2.3.dist-info/LICENSE
cerebellum-0.2.3.dist-info/METADATA
cerebellum-0.2.3.dist-info/WHEEL
cerebellum-0.2.3.dist-info/RECORD
